inspire_json_merger/__init__.py
inspire_json_merger/api.py
inspire_json_merger/comparators.py
inspire_json_merger/config.py
inspire_json_merger/postprocess.py
inspire_json_merger/pre_filters.py
inspire_json_merger/utils.py
inspire_json_merger-11.0.44.dist-info/licenses/LICENSE
tests/__init__.py
tests/conftest.py
inspire_json_merger-11.0.44.dist-info/METADATA
inspire_json_merger-11.0.44.dist-info/WHEEL
inspire_json_merger-11.0.44.dist-info/top_level.txt
inspire_json_merger-11.0.44.dist-info/RECORD
