Metadata-Version: 2.4
Name: inspire-json-merger
Version: 11.0.44
Summary: INSPIRE-specific configuration of the JSON Merger.
Home-page: https://github.com/inspirehep/inspire-json-merger
Author: CERN
Author-email: admin@inspirehep.net
License: GPLv3
Platform: any
Classifier: Development Status :: 4 - Beta
Classifier: Environment :: Web Environment
Classifier: Intended Audience :: Developers
Classifier: License :: OSI Approved :: GNU General Public License v3 (GPLv3)
Classifier: Operating System :: OS Independent
Classifier: Programming Language :: Python
Classifier: Programming Language :: Python :: 2
Classifier: Programming Language :: Python :: 2.7
Classifier: Programming Language :: Python :: 3
Classifier: Programming Language :: Python :: 3.6
Classifier: Topic :: Internet :: WWW/HTTP :: Dynamic Content
Classifier: Topic :: Software Development :: Libraries :: Python Modules
License-File: LICENSE
Requires-Dist: munkres==1.0.12
Requires-Dist: inspire-utils>=3.0.0,~=3.0
Requires-Dist: json-merger[contrib]>=0.7.18,~=0.0
Requires-Dist: pyrsistent>=0.14.0,~=0.0
Provides-Extra: docs
Provides-Extra: tests
Requires-Dist: decorator>=4.1.2,~=4.0; extra == "tests"
Requires-Dist: inspire-schemas==61.5.31; extra == "tests"
Requires-Dist: mock>=2.0.0,~=2.0; extra == "tests"
Requires-Dist: pytest-cov>=2.5.1,~=2.0; extra == "tests"
Requires-Dist: pytest>=4.6.0,~=4.0; python_version <= "2.7" and extra == "tests"
Requires-Dist: pytest>=8.0.2,~=8.0; python_version >= "3.6" and extra == "tests"
Provides-Extra: dev
Requires-Dist: pre-commit==3.5.0; extra == "dev"
Provides-Extra: all
Requires-Dist: decorator>=4.1.2,~=4.0; extra == "all"
Requires-Dist: inspire-schemas==61.5.31; extra == "all"
Requires-Dist: mock>=2.0.0,~=2.0; extra == "all"
Requires-Dist: pytest-cov>=2.5.1,~=2.0; extra == "all"
Requires-Dist: pytest>=4.6.0,~=4.0; python_version <= "2.7" and extra == "all"
Requires-Dist: pytest>=8.0.2,~=8.0; python_version >= "3.6" and extra == "all"
Requires-Dist: pre-commit==3.5.0; extra == "all"
Requires-Dist: decorator>=4.1.2,~=4.0; extra == "all"
Requires-Dist: inspire-schemas==61.5.31; extra == "all"
Requires-Dist: mock>=2.0.0,~=2.0; extra == "all"
Requires-Dist: pytest-cov>=2.5.1,~=2.0; extra == "all"
Requires-Dist: pytest>=4.6.0,~=4.0; python_version <= "2.7" and extra == "all"
Requires-Dist: pytest>=8.0.2,~=8.0; python_version >= "3.6" and extra == "all"
Requires-Dist: pre-commit==3.5.0; extra == "all"
Dynamic: author
Dynamic: author-email
Dynamic: classifier
Dynamic: description
Dynamic: home-page
Dynamic: license
Dynamic: license-file
Dynamic: platform
Dynamic: provides-extra
Dynamic: requires-dist
Dynamic: summary
